Metadata-Version: 1.0
Name: fuck-snapshot
Version: 0.0.1
Summary: a easy snap js
Home-page: UNKNOWN
Author: jnddd
Author-email: 122296743@qq.com
License: UNKNOWN
Platform: UNKNOWN
